LICENCE.txt
README.md
pyproject.toml
py_snmp_sync/__init__.py
py_snmp_sync/snmp_sync.py
py_snmp_sync.egg-info/PKG-INFO
py_snmp_sync.egg-info/SOURCES.txt
py_snmp_sync.egg-info/dependency_links.txt
py_snmp_sync.egg-info/requires.txt
py_snmp_sync.egg-info/top_level.txt
tests/test_sync_snmp.py