Metadata-Version: 2.4
Name: py-snmp-sync
Version: 1.0.1
Summary: Lightweight synchronous SNMPv1 Client implemented as a PySNMP wrapper optimized for sequential queries
Author: Ircama
License-Expression: EUPL-1.2
Project-URL: Homepage, https://github.com/Ircama/py-snmp-sync
Requires-Python: >=3.7
License-File: LICENCE.txt
Requires-Dist: pysnmp>=7.0.0
Dynamic: license-file
